optimize_images_x/__init__.py
optimize_images_x/__main__.py
optimize_images_x/calcs.py
optimize_images_x/global_setup.py
optimize_images_x/search_images.py
optimize_images_x/task.py
optimize_images_x/task_conversion.py
optimize_images_x/watch.py
optimize_images_x/db/__init__.py
optimize_images_x/db/app_settings.py
optimize_images_x/db/app_stats.py
optimize_images_x/db/base.py
optimize_images_x/db/task_settings.py
optimize_images_x/gui/__init__.py
optimize_images_x/gui/about_window.py
optimize_images_x/gui/app_status.py
optimize_images_x/gui/base_app.py
optimize_images_x/gui/main_window.py
optimize_images_x/gui/settings_window.py
optimize_images_x/gui/extra_tk_utilities/__init__.py
optimize_images_x/gui/extra_tk_utilities/auto_scrollbar.py
optimize_images_x/gui/extra_tk_utilities/status_bar.py
optimize_images_x/images/icons/delete.png
optimize_images_x/images/icons/eye.png
optimize_images_x/images/icons/file-plus.png
optimize_images_x/images/icons/folder-plus.png
optimize_images_x/images/icons/settings.png
optimize_images_x-0.9.2b0.dist-info/LICENSE
optimize_images_x-0.9.2b0.dist-info/METADATA
optimize_images_x-0.9.2b0.dist-info/WHEEL
optimize_images_x-0.9.2b0.dist-info/entry_points.txt
optimize_images_x-0.9.2b0.dist-info/top_level.txt
optimize_images_x-0.9.2b0.dist-info/RECORD
