Metadata-Version: 2.1
Name: optimize-images-x
Version: 0.9.2b0
Summary: A desktop app written in Python, that exposes and unlocks the full power of Optimize Images in a nice graphical user interface, to help you reduce the file size of images.
Home-page: https://no-title.victordomingos.com/projects/optimize-images-x/
Author: Victor Domingos
License: MIT
Project-URL: Documentation, https://github.com/victordomingos/optimize-images-x/
Project-URL: Source, https://github.com/victordomingos/optimize-images-x
Project-URL: Bug Reports, https://github.com/victordomingos/optimize-images-x/issues
Keywords: python3 pythonista-ios pil pillow image-processing image-compression image-optimization image-optimisation seo seo-optimization website-performance gui recursive non-recursive
Platform: UNKNOWN
Classifier: Development Status :: 4 - Beta
Classifier: Environment :: MacOS X
Classifier: Intended Audience :: End Users/Desktop
Classifier: Intended Audience :: Developers
Classifier: Intended Audience :: Information Technology
Classifier: License :: OSI Approved :: MIT License
Classifier: Natural Language :: English
Classifier: Operating System :: OS Independent
Classifier: Operating System :: MacOS :: MacOS X
Classifier: Operating System :: Microsoft :: Windows
Classifier: Operating System :: Unix
Classifier: Operating System :: POSIX :: Linux 
Classifier: Programming Language :: Python :: 3
Classifier: Programming Language :: Python :: 3.7
Classifier: Programming Language :: Python :: 3.8
Classifier: Programming Language :: Python :: 3.8
Classifier: Programming Language :: Python :: 3.9
Classifier: Topic :: Utilities
Classifier: Topic :: Multimedia :: Graphics
Classifier: Topic :: Multimedia :: Graphics :: Graphics Conversion
Requires-Python: >=3.7
Requires-Dist: optimize-images (==1.5.0)
Requires-Dist: pillow (>=8.2.0)
Requires-Dist: piexif (==1.1.3)
Requires-Dist: watchdog (==2.1.2)
